pulsars/.DS_Store
pulsars/__init__.py
pulsars/gui/app.py
pulsars/gui/assets/pulsars-logo.png
pulsars/gui/assets/pulsars-white.png
pulsars/gui/assets/pulsars.png
pulsars/gui/assets/sps-geo.png
pulsars/gui/nabla_geo_page.py
pulsars/gui/nabla_home.py
pulsars/gui/nabla_materials.py
pulsars/gui/nabla_results.py
pulsars/gui/nabla_solver.py
pulsars/gui/nabla_style.css
pulsars/gui/pulsarsGUI.sh
pulsars/gui/readtoml.py
pulsars/gui/test.toml
pulsars/gui/test1.py
pulsars/gui/widgets.py
pulsars-0.0.6.dist-info/METADATA
pulsars-0.0.6.dist-info/WHEEL
pulsars-0.0.6.dist-info/RECORD
