Metadata-Version: 2.1
Name: pulsars
Version: 0.0.6
Summary: A Practical Machine Learning System for Applied Research
License: MIT
Author: altar31
Author-email: damien.sicard31@gmail.com
Requires-Python: >=3.10,<4.0
Classifier: License :: OSI Approved :: MIT License
Classifier: Programming Language :: Python :: 3
Classifier: Programming Language :: Python :: 3.10
Classifier: Programming Language :: Python :: 3.11
Requires-Dist: click (>=8.1.3,<9.0.0)
Requires-Dist: keras (>=2.12.0,<3.0.0)
Requires-Dist: matplotlib (>=3.7.1,<4.0.0)
Requires-Dist: mlflow (>=2.4.1,<3.0.0)
Requires-Dist: numpy (>=1.25.0,<2.0.0)
Requires-Dist: pandas (>=2.0.2,<3.0.0)
Requires-Dist: seaborn (>=0.12.2,<0.13.0)
Requires-Dist: tomli (>=2.0.1,<3.0.0)
Requires-Dist: xgboost (>=1.7.6,<2.0.0)
